mylib_004/__init__.py
mylib_004-0.1.dist-info/LICENSE.txt
mylib_004-0.1.dist-info/METADATA
mylib_004-0.1.dist-info/WHEEL
mylib_004-0.1.dist-info/top_level.txt
mylib_004-0.1.dist-info/RECORD
