Metadata-Version: 2.1
Name: mylib-004
Version: 0.1
Summary: for calculating square
Author: Ajit
Author-email: ingoleajit1997@gmail.com
Classifier: Programming Language :: Python :: 3
Classifier: License :: OSI Approved :: MIT License
Classifier: Operating System :: OS Independent
License-File: LICENSE.txt
